ttim/__init__.py
ttim/aquifer.py
ttim/aquifer_parameters.py
ttim/besselnumba.py
ttim/besselnumba_total.py
ttim/circareasink.py
ttim/circinhom.py
ttim/element.py
ttim/equation.py
ttim/fit.py
ttim/inhom1d.py
ttim/invlapnumba.py
ttim/kuhlman_invlap.py
ttim/linedoublet.py
ttim/linedoublet1d.py
ttim/linesink.py
ttim/linesink1d.py
ttim/model.py
ttim/plots.py
ttim/stripareasink.py
ttim/trace.py
ttim/version.py
ttim/well.py
ttim-0.7.2.dist-info/licenses/LICENSE
ttim-0.7.2.dist-info/METADATA
ttim-0.7.2.dist-info/WHEEL
ttim-0.7.2.dist-info/top_level.txt
ttim-0.7.2.dist-info/RECORD
