Metadata-Version: 2.4
Name: ttim
Version: 0.7.2
Summary: Transient multi-layer AEM Model
Author: Mark Bakker
Maintainer-email: Mark Bakker <markbak@gmail.com>, Davíd Brakenhoff <d.brakenhoff@artesia-water.nl>
License: The MIT License (MIT)
Project-URL: homepage, https://github.com/mbakker7/ttim
Project-URL: repository, https://github.com/mbakker7/ttim
Project-URL: documentation, http://mbakker7.github.io/ttim/docs/builddocs/html/index.html
Keywords: hydrology,groundwater,model,analytic element method
Classifier: Development Status :: 4 - Beta
Classifier: Intended Audience :: Science/Research
Classifier: Intended Audience :: Other Audience
Classifier: License :: OSI Approved :: MIT License
Classifier: Operating System :: Microsoft :: Windows
Classifier: Operating System :: POSIX
Classifier: Operating System :: Unix
Classifier: Operating System :: MacOS
Classifier: Programming Language :: Python
Classifier: Programming Language :: Python :: 3
Classifier: Programming Language :: Python :: 3.10
Classifier: Programming Language :: Python :: 3.11
Classifier: Programming Language :: Python :: 3.12
Classifier: Programming Language :: Python :: 3 :: Only
Classifier: Topic :: Scientific/Engineering :: Hydrology
Requires-Python: >=3.10
License-File: LICENSE
Requires-Dist: numpy
Requires-Dist: scipy
Requires-Dist: numba
Requires-Dist: matplotlib
Requires-Dist: lmfit
Requires-Dist: pandas
Provides-Extra: ci
Requires-Dist: pytest; extra == "ci"
Requires-Dist: pytest-cov; extra == "ci"
Requires-Dist: pytest-sugar; extra == "ci"
Requires-Dist: jupyter; extra == "ci"
Requires-Dist: shapely; extra == "ci"
Requires-Dist: coveralls; extra == "ci"
Requires-Dist: timml; extra == "ci"
Provides-Extra: docs
Requires-Dist: ttim[ci]; extra == "docs"
Requires-Dist: sphinx; extra == "docs"
Requires-Dist: sphinx-design; extra == "docs"
Requires-Dist: pydata-sphinx-theme; extra == "docs"
Requires-Dist: numpydoc; extra == "docs"
Requires-Dist: myst_nb; extra == "docs"
Requires-Dist: sphinxcontrib-bibtex; extra == "docs"
Requires-Dist: sphinx-autoapi; extra == "docs"
Dynamic: license-file
